{
  "posts": [
    {
      "id": 420,
      "title": "post 420",
      "description": "post 420 d",
      "email": "asd@gmail.com"
    },
    {
      "id": 424,
      "title": "post 424",
      "description": "post 424 d",
      "email": "asdf@and.com.bd"
    },
    {
      "id": 425,
      "title": "new post ",
      "description": "new post ",
      "email": "aa@aa"
    },
    {
      "id": 426,
      "title": "new post title",
      "description": "new post title",
      "email": "ww@22"
    },
    {
      "id": 427,
      "title": "ewdfwef",
      "description": "ewfewfwef",
      "email": "vv@gm.com"
    },
    {
      "id": 428,
      "title": "dfefewf",
      "description": "wefewf",
      "email": "eer@fewf"
    },
    {
      "id": 429,
      "title": "new 1",
      "description": "new 1",
      "email": "aa@aa"
    },
    {
      "id": 430,
      "title": "wewf",
      "description": "wrfw3rf",
      "email": "aa@aa"
    },
    {
      "id": 431,
      "title": "nwewdw",
      "description": "ewfewfewf",
      "email": "aa@aa"
    },
    {
      "id": 432,
      "title": "fewfewfewf",
      "description": "ewfewfewfewf",
      "email": "ww2@qwdeqw"
    },
    {
      "id": 433,
      "title": "dscvv",
      "description": "ewfewf",
      "email": "ee@ee"
    },
    {
      "id": 434,
      "title": "ewfewf",
      "description": "ewfewfewf",
      "email": "gg@ef"
    },
    {
      "id": 435,
      "postTitle": "post 1",
      "postTitleOtherLang": "post 1@",
      "postSeoUrl": "www.post1.com",
      "postFeatured": "Yes",
      "postContent": "post 1 content"
    }
  ],
  "comments": [
    {
      "id": 1,
      "body": "some comment 1",
      "postId": 1
    },
    {
      "id": 2,
      "body": "some comment 2",
      "postId": 1
    },
    {
      "id": 3,
      "body": "some comment 3",
      "postId": 1
    },
    {
      "id": 4,
      "body": "some comment 4",
      "postId": 1
    },
    {
      "id": 5,
      "body": "some comment 5",
      "postId": 1
    },
    {
      "id": 6,
      "body": "some comment 6",
      "postId": 1
    },
    {
      "body": "some comment 11",
      "postId": 1,
      "id": 11
    },
    {
      "id": 14,
      "body": "some content 14",
      "postId": 1
    },
    {
      "id": 15,
      "body": "some content 15",
      "postId": 1
    },
    {
      "id": 16,
      "body": "some content 16",
      "postId": 2
    },
    {
      "id": 100,
      "body": "some content 100",
      "postId": 2
    },
    {
      "id": 200,
      "body": "some content 200",
      "postId": 6
    },
    {
      "id": 3000,
      "body": "some content 3000",
      "postId": 6
    }
  ]
}